pdf417/__init__.py
pdf417/codes.py
pdf417/compaction.py
pdf417/console.py
pdf417/data.py
pdf417/encoding.py
pdf417/error_correction.py
pdf417/rendering.py
pdf417/util.py
pdf417-0.8.1.dist-info/LICENSE
pdf417-0.8.1.dist-info/METADATA
pdf417-0.8.1.dist-info/WHEEL
pdf417-0.8.1.dist-info/entry_points.txt
pdf417-0.8.1.dist-info/top_level.txt
pdf417-0.8.1.dist-info/RECORD
