Metadata-Version: 2.1
Name: pdf417
Version: 0.8.1
Summary: PDF417 2D barcode generator for Python
Home-page: https://github.com/mosquito/pdf417/
Author: Ivan Habunek
Author-email: ivan.habunek@gmail.com
License: MIT
Keywords: pdf417 2d barcode generator
Platform: UNKNOWN
Classifier: Development Status :: 4 - Beta
Classifier: Intended Audience :: Developers
Classifier: License :: OSI Approved :: MIT License
Classifier: Programming Language :: Python :: 2
Classifier: Programming Language :: Python :: 2.7
Classifier: Programming Language :: Python :: 3
Classifier: Programming Language :: Python :: 3.3
Classifier: Programming Language :: Python :: 3.4
Classifier: Programming Language :: Python :: 3.5
Classifier: Programming Language :: Python :: 3.6
Provides-Extra: pillow-simd
Provides-Extra: pillow
